django_datatables_too/__init__.py
django_datatables_too/mixins.py
django_datatables_too/models.py
django_datatables_too/views.py
django_datatables_too-0.1.4.dist-info/LICENSE
django_datatables_too-0.1.4.dist-info/METADATA
django_datatables_too-0.1.4.dist-info/WHEEL
django_datatables_too-0.1.4.dist-info/top_level.txt
django_datatables_too-0.1.4.dist-info/RECORD
