Metadata-Version: 2.1
Name: django-datatables-too
Version: 0.1.4
Summary: Django integration with jQuery DataTables.
Home-page: https://github.com/tsantor/django-datatables-too
Author: Tim Santor
Author-email: tsantor@xstudios.com
License: MIT
Keywords: django-datatables-too
Platform: UNKNOWN
Classifier: Development Status :: 5 - Production/Stable
Classifier: Intended Audience :: Developers
Classifier: Topic :: Software Development :: Libraries
Classifier: License :: OSI Approved :: MIT License
Classifier: Natural Language :: English
Classifier: Programming Language :: Python :: 3.6
Classifier: Programming Language :: Python :: 3.7
Classifier: Programming Language :: Python :: 3.8
Classifier: Programming Language :: Python :: 3.9
License-File: LICENSE
Requires-Dist: querystring-parser (==1.2.4)
